openeo/__init__.py
openeo/_version.py
openeo/capabilities.py
openeo/config.py
openeo/dates.py
openeo/metadata.py
openeo/processes.py
openeo/util.py
openeo/api/__init__.py
openeo/api/logs.py
openeo/api/process.py
openeo/extra/__init__.py
openeo/extra/artifacts/__init__.py
openeo/extra/artifacts/_artifact_helper_abc.py
openeo/extra/artifacts/_backend.py
openeo/extra/artifacts/_config.py
openeo/extra/artifacts/_uri.py
openeo/extra/artifacts/artifact_helper.py
openeo/extra/artifacts/exceptions.py
openeo/extra/artifacts/_s3sts/__init__.py
openeo/extra/artifacts/_s3sts/artifact_helper.py
openeo/extra/artifacts/_s3sts/config.py
openeo/extra/artifacts/_s3sts/model.py
openeo/extra/artifacts/_s3sts/sts.py
openeo/extra/artifacts/_s3sts/tracer.py
openeo/extra/job_management/__init__.py
openeo/extra/job_management/_interface.py
openeo/extra/job_management/_job_db.py
openeo/extra/job_management/_job_splitting.py
openeo/extra/job_management/_manager.py
openeo/extra/job_management/_thread_worker.py
openeo/extra/job_management/process_based.py
openeo/extra/job_management/stac_job_db.py
openeo/extra/spectral_indices/__init__.py
openeo/extra/spectral_indices/spectral_indices.py
openeo/extra/spectral_indices/resources/extra-indices-dict.json
openeo/extra/spectral_indices/resources/awesome-spectral-indices/LICENSE
openeo/extra/spectral_indices/resources/awesome-spectral-indices/bands.json
openeo/extra/spectral_indices/resources/awesome-spectral-indices/constants.json
openeo/extra/spectral_indices/resources/awesome-spectral-indices/spectral-indices-dict.json
openeo/internal/__init__.py
openeo/internal/documentation.py
openeo/internal/graph_building.py
openeo/internal/jupyter.py
openeo/internal/process_graph_visitor.py
openeo/internal/warnings.py
openeo/internal/processes/__init__.py
openeo/internal/processes/builder.py
openeo/internal/processes/generator.py
openeo/internal/processes/parse.py
openeo/local/__init__.py
openeo/local/collections.py
openeo/local/connection.py
openeo-0.47.0.dist-info/licenses/LICENSE
openeo-0.47.0.dist-info/METADATA
openeo-0.47.0.dist-info/WHEEL
openeo-0.47.0.dist-info/entry_points.txt
openeo-0.47.0.dist-info/top_level.txt
openeo-0.47.0.dist-info/RECORD
