Metadata-Version: 2.4
Name: openeo
Version: 0.47.0
Summary: Client API for openEO
Home-page: https://github.com/Open-EO/openeo-python-client
Author: Jeroen Dries
Author-email: jeroen.dries@vito.be
Project-URL: Documentation, https://open-eo.github.io/openeo-python-client/
Project-URL: Source Code, https://github.com/Open-EO/openeo-python-client
Project-URL: Bug Tracker, https://github.com/Open-EO/openeo-python-client/issues
Project-URL: Changelog, https://github.com/Open-EO/openeo-python-client/blob/master/CHANGELOG.md
Classifier: Programming Language :: Python :: 3.8
Classifier: Programming Language :: Python :: 3.9
Classifier: Programming Language :: Python :: 3.10
Classifier: Programming Language :: Python :: 3.11
Classifier: Programming Language :: Python :: 3.12
Classifier: Programming Language :: Python :: 3.13
Classifier: License :: OSI Approved :: Apache Software License
Classifier: Development Status :: 5 - Production/Stable
Classifier: Operating System :: OS Independent
Requires-Python: >=3.8
License-File: LICENSE
Requires-Dist: requests>=2.26.0
Requires-Dist: urllib3>=1.9.0
Requires-Dist: shapely>=1.6.4
Requires-Dist: numpy>=1.17.0
Requires-Dist: xarray<2025.01.2,>=0.12.3
Requires-Dist: pandas>0.20.0
Requires-Dist: pystac>=1.5.0
Requires-Dist: deprecated>=1.2.12
Requires-Dist: oschmod>=0.3.12; sys_platform == "win32"
Requires-Dist: importlib_resources; python_version < "3.9"
Provides-Extra: tests
Requires-Dist: pytest>=4.5.0; extra == "tests"
Requires-Dist: mock; extra == "tests"
Requires-Dist: requests-mock>=1.8.0; extra == "tests"
Requires-Dist: httpretty>=1.1.4; extra == "tests"
Requires-Dist: urllib3<2.3.0; extra == "tests"
Requires-Dist: netCDF4>=1.7.0; extra == "tests"
Requires-Dist: geopandas>=0.14; python_version >= "3.9" and extra == "tests"
Requires-Dist: geopandas; extra == "tests"
Requires-Dist: flake8>=5.0.0; extra == "tests"
Requires-Dist: time_machine>=2.13.0; extra == "tests"
Requires-Dist: pyproj>=3.2.0; extra == "tests"
Requires-Dist: dirty_equals>=0.8.0; extra == "tests"
Requires-Dist: pyarrow>=10.0.1; extra == "tests"
Requires-Dist: python-dateutil>=2.7.0; extra == "tests"
Requires-Dist: pystac-client>=0.7.5; extra == "tests"
Requires-Dist: moto>=5.0.0; extra == "tests"
Requires-Dist: boto3; extra == "tests"
Requires-Dist: botocore; extra == "tests"
Provides-Extra: dev
Requires-Dist: pytest>=4.5.0; extra == "dev"
Requires-Dist: mock; extra == "dev"
Requires-Dist: requests-mock>=1.8.0; extra == "dev"
Requires-Dist: httpretty>=1.1.4; extra == "dev"
Requires-Dist: urllib3<2.3.0; extra == "dev"
Requires-Dist: netCDF4>=1.7.0; extra == "dev"
Requires-Dist: geopandas>=0.14; python_version >= "3.9" and extra == "dev"
Requires-Dist: geopandas; extra == "dev"
Requires-Dist: flake8>=5.0.0; extra == "dev"
Requires-Dist: time_machine>=2.13.0; extra == "dev"
Requires-Dist: pyproj>=3.2.0; extra == "dev"
Requires-Dist: dirty_equals>=0.8.0; extra == "dev"
Requires-Dist: pyarrow>=10.0.1; extra == "dev"
Requires-Dist: python-dateutil>=2.7.0; extra == "dev"
Requires-Dist: pystac-client>=0.7.5; extra == "dev"
Requires-Dist: moto>=5.0.0; extra == "dev"
Requires-Dist: sphinx; extra == "dev"
Requires-Dist: sphinx-autodoc-annotation; extra == "dev"
Requires-Dist: sphinx-autodoc-typehints>=2.2.3; extra == "dev"
Requires-Dist: myst-parser; extra == "dev"
Requires-Dist: types-boto3-s3; extra == "dev"
Requires-Dist: types-boto3-sts; extra == "dev"
Requires-Dist: boto3; extra == "dev"
Requires-Dist: botocore; extra == "dev"
Provides-Extra: docs
Requires-Dist: sphinx; extra == "docs"
Requires-Dist: sphinx-autodoc-annotation; extra == "docs"
Requires-Dist: sphinx-autodoc-typehints>=2.2.3; extra == "docs"
Requires-Dist: myst-parser; extra == "docs"
Provides-Extra: oschmod
Requires-Dist: oschmod>=0.3.12; extra == "oschmod"
Provides-Extra: localprocessing
Requires-Dist: rioxarray>=0.13.0; extra == "localprocessing"
Requires-Dist: pyproj; extra == "localprocessing"
Requires-Dist: openeo_pg_parser_networkx>=2023.5.1; extra == "localprocessing"
Requires-Dist: openeo_processes_dask[implementations]>=2023.7.1; extra == "localprocessing"
Provides-Extra: jupyter
Requires-Dist: ipyleaflet>=0.17.0; extra == "jupyter"
Requires-Dist: ipython; extra == "jupyter"
Provides-Extra: artifacts
Requires-Dist: boto3; extra == "artifacts"
Requires-Dist: botocore; extra == "artifacts"
Dynamic: author
Dynamic: author-email
Dynamic: classifier
Dynamic: description
Dynamic: description-content-type
Dynamic: home-page
Dynamic: license-file
Dynamic: project-url
Dynamic: provides-extra
Dynamic: requires-dist
Dynamic: requires-python
Dynamic: summary
